


[{"content":"","date":"30 October 2024","externalUrl":null,"permalink":"/series/denorma/","section":"Series","summary":"","title":"DeNorma","type":"series"},{"content":"","date":"30 October 2024","externalUrl":null,"permalink":"/","section":"Estio","summary":"","title":"Estio","type":"page"},{"content":"","date":"30 October 2024","externalUrl":null,"permalink":"/tags/gis/","section":"Tags","summary":"","title":"GIS","type":"tags"},{"content":"","date":"30 October 2024","externalUrl":null,"permalink":"/tags/how-to/","section":"Tags","summary":"","title":"How-To","type":"tags"},{"content":"","date":"30 October 2024","externalUrl":null,"permalink":"/tags/norma/","section":"Tags","summary":"","title":"Norma","type":"tags"},{"content":"","date":"30 October 2024","externalUrl":null,"permalink":"/posts/","section":"Posts","summary":"","title":"Posts","type":"posts"},{"content":"","date":"30 October 2024","externalUrl":null,"permalink":"/series/","section":"Series","summary":"","title":"Series","type":"series"},{"content":"","date":"30 October 2024","externalUrl":null,"permalink":"/tags/series/","section":"Tags","summary":"","title":"Series","type":"tags"},{"content":"","date":"30 October 2024","externalUrl":null,"permalink":"/tags/sig/","section":"Tags","summary":"","title":"SIG","type":"tags"},{"content":"","date":"30 October 2024","externalUrl":null,"permalink":"/tags/","section":"Tags","summary":"","title":"Tags","type":"tags"},{"content":" Is normalization good? # Yes and no, it depends\u0026hellip;\nThe normalization and harmonization of data is something I consider essential, it ensures that information can be read quickly\u0026hellip;\nAlthough sometimes, when you come across data that\u0026rsquo;s too structured, like, I don\u0026rsquo;t know, INSPIRE \u0026#x1f440;, you lose track of it, to the point where it seems complicated, just because needs to be\n\u0026hellip;we have a better perception and clarity in the application or use of the information, but also a greater guarantee that the information is correct with its replication/propagation. Which is great, especially when we\u0026rsquo;re dealing with information on land registry, or with land planning and management, in the various types of Land Management Instruments (IGT) that exist in Portugal.\n- What about when it\u0026rsquo;s not? The normalization of ideologies and abject ideas is one of those cases, and then whoever holds power also tends to define what is “normal” and what is not, and we\u0026rsquo;ve all had History at school, or read or seen enough fiction to know what that leads to.\nBut back to data, they also say that the “denormalization” of data can be a good thing, especially when storage space is not an issue. This is because it allows the data to be read faster and better, and therefore with better performance, and even less overhead than a relational database one, especially when comparing it to ultra-normalized data.\nBut these memes exist\u0026hellip;\nor this one.\nBut sometimes it can make sense to use unstructured data, perhaps a subject for another post later on.\nThe Norms # As I mentioned in a previous post, and I\u0026rsquo;ve also hinted in this one, part of my work is in land planning and management. So in this case, in order to develop land management instruments (IGT), the standards to be implemented would be:\nData Model and Systematization of Graphic Information for Municipal Master Plans (PDM);\nTechnical Standard on the Production and Reproduction of National Ecological Reserve (REN) Delimitation Maps.\nBoth published in the Portugal\u0026rsquo;s Official Law Journal, in Aviso nº. 9282/2021 of May 17, as published here on the Direção Geral do Território website.\nIn other words, some time has passed, which is great, because it allows us to see what the results have been, what difficulties they\u0026rsquo;ve encountered in implementing them and why they\u0026rsquo;re not\u0026hellip; \u0026#x1f64a; almost spoiled the suspense.\nThe Objective # The idea, then, in this series of posts, is to focus on one of these standards, in this case, the National Ecological Reserve (REN) standard, and its implementation in FOSS4G technology1, while at the same time trying to comply with another legal standard, National Digital Interoperability Regulation (RNID).\n- What about the PDM standard? Let\u0026rsquo;s take it easy, first the REN, and if it all goes well, why not. But a lot of people have been working on this for some time.\nqgispt/qgis_pt_norma_pdm2qgis Aplicação da Norma Técnica sobre Modelo de Dados para o Plano Director Municipal no QGIS Python 7 8 The order of this blog series # As it\u0026rsquo;s a rather boring subject, made up of a lot of annoyances, I\u0026rsquo;m going to put it in parts, and try to follow more or less this alignment:\nContextualize these IGTs and the current state and why of the standards; We\u0026rsquo;re going to have to take a look, at least once, diagonally or scraping the surface, please bare with me. And their current implementation; Make the symbology in the [QGIS] environment(https://qgis.org/); Look at the OGC Geopackage spec and try to create the data model on it; And in the end, wrap it all up as well as possible and make it available to everyone. See you next time, for the second part.\nFree and Open Source Software for Geospatial\u0026#160;\u0026#x21a9;\u0026#xfe0e;\n","date":"30 October 2024","externalUrl":null,"permalink":"/posts/1730286641658-denorma/","section":"Posts","summary":"Is normalization good?","title":"The DeNorm - part 1","type":"posts"},{"content":"","date":"28 October 2024","externalUrl":null,"permalink":"/categories/blowfish/","section":"Categories","summary":"","title":"Blowfish","type":"categories"},{"content":"","date":"28 October 2024","externalUrl":null,"permalink":"/tags/blowfish/","section":"Tags","summary":"","title":"Blowfish","type":"tags"},{"content":"","date":"28 October 2024","externalUrl":null,"permalink":"/categories/","section":"Categories","summary":"","title":"Categories","type":"categories"},{"content":"","date":"28 October 2024","externalUrl":null,"permalink":"/tags/hugo/","section":"Tags","summary":"","title":"Hugo","type":"tags"},{"content":"","date":"28 October 2024","externalUrl":null,"permalink":"/categories/open-source/","section":"Categories","summary":"","title":"Open-Source","type":"categories"},{"content":"So, Blowfish hmmm!!! Why?\nnunocoracao/blowfish Personal Website \u0026amp; Blog Theme for Hugo HTML 1466 408 Blowfish # Well it was quite a simple decision, after finding it, and it came down to some of the features, but mainly because:\nit looked good; markdown support; easily updatable; good looking; multi language; and it also looked good. So by the end of last year and throughout the start of this one, I was wondering, yeah, I\u0026rsquo;m kind of a overthinker or a late bloomer when it comes to execution cause I get tangled up in the thinking part, about creating a new personal page / blog. At that time there was a lot going on with my life, and by a lot, I mean that I was thinking about leaving my daily work, focus only at the company that was in a new stage with a new foreign investor that joined us. So it was hectic and I thought\u0026hellip;\n\u0026ldquo;I should write, it would allow me to concentrate on only one thing for a brief period of time of the day\u0026hellip;write about what was happening and also exorcise it by putting it on something!\u0026rdquo;\nSeemed like a great plan, but did none of it.\nAlternatives # At the time, I was also messing a lot with LIDAR, trying to process point clouds, for forestry metrics and was using R for it.\nSo I stumble on Quarto, and it seemed really cool, lots of hype around it, seemed simpler than blogdown. So I dwelled a bit with it using R-Studio, but I didn\u0026rsquo;t have the time to make it good looking.\nAlso looked at Hugo, Astro and some other\u0026rsquo;s. And it was when I looked at Hugo that I discovered Blowfish, created by a fellow portuguese, Nuno Coração. And it seemed right up my alley with the command line tools, I have a soft spot for cli tools, to ease the managing of it\u0026hellip;\n\u0026hellip;😳😯😲😮😍 OMG it as 8-bit blowfish in the command line!!!\nSo sort of quick how-to. # Requirements # node latest hugo git In case you are on fedora, like I\u0026rsquo;m, just do:\nsudo dnf install nodejs hugo git -y This is one of the cool perks of Fedora, up to date packages.\nNext\u0026hellip; # \u0026hellip;run this on your command-line\nnpx blowfish-tools Select \u0026ldquo;Setup a new website with Blowfish\u0026rdquo;, and point to the folder you want. After that, you just start to configure it, just mess around, best way to learn, really is, trial and error! You can test and see the result of your experiences on the browser, by navigating to localhost:1313.\nDeploying it # I used github, and to ensure it deploy correctly, created an action / workflow in the repo, like this one.\nname: github pages on: push: branches: - main # Set a branch to deploy pull_request: jobs: deploy: runs-on: ubuntu-22.04 steps: - uses: actions/checkout@v3 with: submodules: true # Fetch Hugo themes (true OR recursive) fetch-depth: 0 # Fetch all history for .GitInfo and .Lastmod - name: Setup Hugo uses: peaceiris/actions-hugo@v2 with: hugo-version: \u0026#39;0.136.5\u0026#39; extended: true - name: Build run: hugo --minify - name: Deploy uses: peaceiris/actions-gh-pages@v3 if: github.ref == \u0026#39;refs/heads/main\u0026#39; with: github_token: ${{ secrets.GITHUB_TOKEN }} publish_dir: ./public And that\u0026rsquo;s that.. # \u0026hellip;and now I just need to worry about writing as often as I can and push the commit to github.\nDown the rabbit hole # Some useful links to get you started, if you need to know more or want to create your own page.\nhttps://n9o.xyz/posts/202310-blowfish-tutorial/ https://blowfish.page/docs/ https://blowfish.page/docs/configuration/ https://blowfish.page/docs/shortcodes/ https://blowfish.page/examples/ ","date":"28 October 2024","externalUrl":null,"permalink":"/posts/1730127710080-blowfish-why/","section":"Posts","summary":"Well it was quite a simple decision, after finding it, and it came down to some of the features, but mainly\u0026hellip;","title":"So, Blowfish, hmmm!!! Why?","type":"posts"},{"content":"","date":"28 October 2024","externalUrl":null,"permalink":"/tags/tutorial/","section":"Tags","summary":"","title":"Tutorial","type":"tags"},{"content":" ESTIO? # So this is a start of something, a new personal page, but also some sort of notebook of what I do, with data, with geospatial. What I learn in my homelabing experiences or something I can\u0026rsquo;t shut up about it, or something i learned for future memory, like a Today I Learned (TIL).\nWill force myself to do a weekly, I hope, post, with something useful, or just something\u0026hellip;but no pressure.\nBut you are probably wondering why \u0026ldquo;Estio\u0026rdquo; for the name of personal website. Well \u0026ldquo;Estio\u0026rdquo; is a portuguese/latin word which means in between, in a period of transition, in between Spring and Autumn, and I sorted feel like that, right now i feel like I\u0026rsquo;m in my “Estio”!\n","date":"25 October 2024","externalUrl":null,"permalink":"/posts/1729858463421-1st-things-1st/","section":"Posts","summary":"ESTIO?","title":"1st things 1st","type":"posts"},{"content":"","date":"25 October 2024","externalUrl":null,"permalink":"/tags/post/","section":"Tags","summary":"","title":"Post","type":"tags"},{"content":"","date":"25 October 2024","externalUrl":null,"permalink":"/tags/rant/","section":"Tags","summary":"","title":"Rant","type":"tags"},{"content":"With over twenty years of experience in forestry engineering, but mainly focused on management, that sent me that the geospatial rabbit hole, specializing in FOSS4G tools. On 2005 try to start GIS FOSS4G startup, and failed, started working in my trade, and on 2012 started another startup with some partners and it’s still going. Right now mainly work in geospatial and land management with an increasing dab of data management. I have a passion for understanding problems and work out innovative solutions so I can leisure or procrastinate longer and better.\nCurrently, work in a Portuguese municipality as a forestry engineer, but also as a geospatial consultant and a data engineer, dwelling through out a some of these areas:\nForestry and wildfire prevention; GIS; Land management, and Urban Planing; Resource and Infrastructure Management, mainly water and sewage utilities. Internet taught homelab afficionado, LIDAR and point cloud addict, and when possible a gamer. Music is my Sanctuary, 50% of Soul Robots. A woodworker wannabe, but still just watching videos.\n","date":"13 June 2022","externalUrl":null,"permalink":"/about/","section":"Estio","summary":"With over twenty years of experience in forestry engineering, but mainly focused on management, that sent me that the geospatial rabbit hole, specializing in FOSS4G tools.","title":"About","type":"page"},{"content":"","externalUrl":null,"permalink":"/authors/","section":"Authors","summary":"","title":"Authors","type":"authors"}]